README.rst
setup.py
LightDB.egg-info/PKG-INFO
LightDB.egg-info/SOURCES.txt
LightDB.egg-info/dependency_links.txt
LightDB.egg-info/top_level.txt
lightdb/__init__.py
lightdb/core.py
lightdb/exceptions.py
lightdb/fields.py
lightdb/models.py
lightdb/query.py