Metadata-Version: 2.1
Name: LightDB
Version: 2.0
Summary: Lightweight JSON Database for Python
Home-page: https://github.com/Fl1yd/LightDB
Download-URL: https://github.com/Fl1yd/LightDB/releases
Author: Fl1yd
Author-email: projects@fl1yd.su
License: MIT
